iohblade/__init__.py
iohblade/assets.py
iohblade/behaviour_metrics.py
iohblade/experiment.py
iohblade/llm.py
iohblade/method.py
iohblade/plots.py
iohblade/problem.py
iohblade/solution.py
iohblade/utils.py
iohblade/webapp.py
iohblade/baselines/__init__.py
iohblade/baselines/modcma.py
iohblade/loggers/__init__.py
iohblade/loggers/base.py
iohblade/loggers/mlflow.py
iohblade/loggers/trackio.py
iohblade/methods/__init__.py
iohblade/methods/eoh.py
iohblade/methods/funsearch.py
iohblade/methods/llamea.py
iohblade/methods/random_search.py
iohblade/methods/reevo.py
iohblade/misc/__init__.py
iohblade/misc/ast.py
iohblade/problems/__init__.py
iohblade/problems/automl.py
iohblade/problems/bbob_sboxcost.py
iohblade/problems/kerneltuner.py
iohblade/problems/mabbob.py
iohblade/problems/photonics.py
iohblade/problems/mabbob/iids.csv
iohblade/problems/mabbob/opt_locs.csv
iohblade/problems/mabbob/weights.csv
iohblade/problems/photonics_instances/__init__.py
iohblade/problems/photonics_instances/exp_photonic.py
iohblade/problems/photonics_instances/problems/__init__.py
iohblade/problems/photonics_instances/problems/brag_mirror.py
iohblade/problems/photonics_instances/problems/ellipsometry_inverse.py
iohblade/problems/photonics_instances/problems/grating2D.py
iohblade/problems/photonics_instances/problems/photonic_problem.py
iohblade/problems/photonics_instances/problems/plasmonic_nanostructure.py
iohblade/problems/photonics_instances/problems/sophisticated_antireflection_design.py
iohblade-0.2.3.dist-info/METADATA
iohblade-0.2.3.dist-info/WHEEL
iohblade-0.2.3.dist-info/entry_points.txt
iohblade-0.2.3.dist-info/licenses/LICENSE
iohblade-0.2.3.dist-info/RECORD
