Metadata-Version: 2.4
Name: iohblade
Version: 0.2.3
Summary: Benchmarking Llm Assisted Design and Evolution of algorithms.
Project-URL: Homepage, https://github.com/XAI-liacs/BLADE
Project-URL: Repository, https://github.com/XAI-liacs/BLADE
Author-email: Niki van Stein <n.van.stein@liacs.leidenuniv.nl>
License-Expression: MIT
License-File: LICENSE
Requires-Python: <4,>=3.11
Requires-Dist: anthropic<1,>=0.57
Requires-Dist: google-genai<2,>=1
Requires-Dist: ioh>=0.3.22
Requires-Dist: joblib<2,>=1.4.2
Requires-Dist: jsonlines<5,>=4.0.0
Requires-Dist: jsonschema<5,>=4.24.0
Requires-Dist: lizard>=1.17.31
Requires-Dist: llamea<2,>=1.1.8
Requires-Dist: mlflow<4,>=3.1.0
Requires-Dist: networkx>=3.5
Requires-Dist: numpy<3,>=2
Requires-Dist: ollama<1,>=0.5.3
Requires-Dist: openai<2,>=1.99.1
Requires-Dist: pandas<3,>=2.2.3
Requires-Dist: plotly>=6.2.0
Requires-Dist: python-constraint2<3,>=2.2.3
Requires-Dist: seaborn>=0.13.2
Requires-Dist: smac>=2.3.1
Requires-Dist: streamlit<2,>=1.35.0
Requires-Dist: tokencost<0.2,>=0.1.26
Requires-Dist: virtualenv>=20.34.0
Requires-Dist: xmltodict<0.15,>=0.14.2
